js.deform-2.0.14-py3.7-nspkg.pth
js/deform/__init__.py
js/deform/tests/conftest.py
js/deform/tests/test_deform.rst
js/deform/tests/test_includeme.py
js.deform-2.0.14.dist-info/LICENSE.txt
js.deform-2.0.14.dist-info/METADATA
js.deform-2.0.14.dist-info/WHEEL
js.deform-2.0.14.dist-info/entry_points.txt
js.deform-2.0.14.dist-info/namespace_packages.txt
js.deform-2.0.14.dist-info/top_level.txt
js.deform-2.0.14.dist-info/RECORD
