Metadata-Version: 2.1
Name: js.deform
Version: 2.0.14
Summary: Fanstatic packaging of deform
Home-page: https://github.com/fanstatic/js.deform
Author: Fanstatic developers
Author-email: kotti@googlegroups.com
License: BSD
Platform: UNKNOWN
Classifier: Development Status :: 6 - Mature
Classifier: Intended Audience :: Developers
Classifier: Programming Language :: Python
Classifier: Programming Language :: Python :: 2
Classifier: Programming Language :: Python :: 2.7
Classifier: Programming Language :: Python :: 3
Classifier: Programming Language :: Python :: 3.6
Classifier: Programming Language :: Python :: 3.7
Classifier: Programming Language :: Python :: 3.8
Classifier: Programming Language :: Python :: 3.9
Classifier: Programming Language :: Python :: Implementation :: CPython
Classifier: Programming Language :: Python :: Implementation :: PyPy
Classifier: Framework :: Pyramid
Classifier: Topic :: Internet :: WWW/HTTP
Classifier: Topic :: Internet :: WWW/HTTP :: WSGI
Classifier: License :: OSI Approved :: BSD License
Requires-Dist: deform (>=2.0.11)
Requires-Dist: fanstatic
Requires-Dist: js.jquery
Requires-Dist: js.jquery-form
Requires-Dist: js.jquery-maskedinput
Requires-Dist: js.jquery-maskmoney
Requires-Dist: js.jquery-sortable
Requires-Dist: js.jquery-timepicker-addon
Requires-Dist: js.jqueryui
Requires-Dist: js.modernizr
Requires-Dist: js.select2
Requires-Dist: js.tinymce
Requires-Dist: setuptools
Provides-Extra: testing
Requires-Dist: pyramid ; extra == 'testing'
Requires-Dist: pyramid-chameleon ; extra == 'testing'
Requires-Dist: pytest (>=3.1) ; extra == 'testing'
Requires-Dist: pytest-cov ; extra == 'testing'
Requires-Dist: pytest-flake8 ; extra == 'testing'
Requires-Dist: setuptools-git ; extra == 'testing'
Requires-Dist: tox ; extra == 'testing'
